{ 
"background-color": "#ffffff",
"border-color": "#dddddd",
"text-width": 450,
"text-height": 648,
"margin-left": 72,
"margin-right": 54,
"margin-right-over": 36,
"margin-top": 72,
"margin-bottom": 36,
"title-sep": 0,
"pgno-sep": 0,
"title-font-family": "Ubuntu",
"title-font-size": 11,
"title-color": "#000088",
"date-font-family": "Ubuntu",
"date-font-size": 11,
"date-color": "#000000",
"pgno-font-family": "Ubuntu",
"pgno-font-size": 11,
"pgno-color": "#000000",
"contd-font-family": "Ubuntu",
"contd-font-size": 11,
"contd-color": "#0000cc",
"margin-left-line-width": 0.5,
"margin-left-line-color": "#ff8888",
"margin-top-line-width": 0.5,
"margin-top-line-color": "#8888ff"
}